{
  "last_updated": "2026-01-01T01:42:23.166035Z",
  "total_matches": 4,
  "matches": [
    {
      "title": "Cry Palace vs Fulham",
      "url": "https://ovogoaal.com/match-updates/crystal-palace-vs-fulham/",
      "time": "18:30",
      "category": "premier",
      "first_level_iframes": [
        "https://ballcontrol.click/home/blog1/"
      ],
      "stream_urls": [
        "https://ballcontrol.click/1111.php",
        "https://storage.googleapis.com/bestinghutjgh1/mux_video_ts1/index-1.m3u8",
        "https://storage.googleapis.com/bestinghutjgh1/mux_video_ts/index-1.m3u8"
      ],
      "stream_count": 3,
      "iframe_details": [
        {
          "url": "https://ballcontrol.click/home/blog1/",
          "nested_iframes": [
            {
              "url": "https://ballcontrol.click/1111.php",
              "nested_iframes": [],
              "stream_urls": [
                "https://storage.googleapis.com/bestinghutjgh1/mux_video_ts1/index-1.m3u8",
                "https://storage.googleapis.com/bestinghutjgh1/mux_video_ts/index-1.m3u8"
              ]
            }
          ],
          "stream_urls": [
            "https://storage.googleapis.com/bestinghutjgh1/mux_video_ts/index-1.m3u8",
            "https://ballcontrol.click/1111.php",
            "https://storage.googleapis.com/bestinghutjgh1/mux_video_ts1/index-1.m3u8"
          ]
        }
      ]
    },
    {
      "title": "Liverpool vs Leeds",
      "url": "https://ovogoaal.com/match-updates/liverpool-vs-leeds-united/",
      "time": "18:30",
      "category": "premier",
      "first_level_iframes": [
        "https://ballcontrol.click/home/blog2/"
      ],
      "stream_urls": [
        "https://ballcontrol.click/2222.php"
      ],
      "stream_count": 1,
      "iframe_details": [
        {
          "url": "https://ballcontrol.click/home/blog2/",
          "nested_iframes": [
            {
              "url": "https://ballcontrol.click/2222.php",
              "nested_iframes": [],
              "stream_urls": []
            }
          ],
          "stream_urls": [
            "https://ballcontrol.click/2222.php"
          ]
        }
      ]
    },
    {
      "title": "Brentford vs Tottenham",
      "url": "https://ovogoaal.com/match-updates/brentford-vs-tottenham-hotspur/",
      "time": "21:00",
      "category": "premier",
      "first_level_iframes": [
        "https://ballcontrol.click/home/blog1/"
      ],
      "stream_urls": [
        "https://ballcontrol.click/1111.php",
        "https://storage.googleapis.com/bestinghutjgh1/mux_video_ts1/index-1.m3u8",
        "https://storage.googleapis.com/bestinghutjgh1/mux_video_ts/index-1.m3u8"
      ],
      "stream_count": 3,
      "iframe_details": [
        {
          "url": "https://ballcontrol.click/home/blog1/",
          "nested_iframes": [
            {
              "url": "https://ballcontrol.click/1111.php",
              "nested_iframes": [],
              "stream_urls": [
                "https://storage.googleapis.com/bestinghutjgh1/mux_video_ts1/index-1.m3u8",
                "https://storage.googleapis.com/bestinghutjgh1/mux_video_ts/index-1.m3u8"
              ]
            }
          ],
          "stream_urls": [
            "https://storage.googleapis.com/bestinghutjgh1/mux_video_ts/index-1.m3u8",
            "https://ballcontrol.click/1111.php",
            "https://storage.googleapis.com/bestinghutjgh1/mux_video_ts1/index-1.m3u8"
          ]
        }
      ]
    },
    {
      "title": "Sunderland vs Man City",
      "url": "https://ovogoaal.com/match-updates/sunderland-vs-manchester-city/",
      "time": "21:00",
      "category": "premier",
      "first_level_iframes": [
        "https://ballcontrol.click/home/blog2/"
      ],
      "stream_urls": [
        "https://ballcontrol.click/2222.php"
      ],
      "stream_count": 1,
      "iframe_details": [
        {
          "url": "https://ballcontrol.click/home/blog2/",
          "nested_iframes": [
            {
              "url": "https://ballcontrol.click/2222.php",
              "nested_iframes": [],
              "stream_urls": []
            }
          ],
          "stream_urls": [
            "https://ballcontrol.click/2222.php"
          ]
        }
      ]
    }
  ]
}