{
  "last_updated": "2025-12-29T01:05:24.892442Z",
  "events": {
    "SUNDAY": [
      {
        "time": "23:00",
        "event": "NBA: Boston Celtics @ Portland Trail Blazers",
        "streams": [
          "https://sportsonline.click/channels/pt/sporttv4.php"
        ]
      },
      {
        "time": "01:10",
        "event": "NFL: Chicago Bears @ San Francisco 49ers",
        "streams": [
          "https://sportsonline.click/channels/hd/hd1.php",
          "https://sportsonline.click/channels/pt/eleven1.php"
        ]
      },
      {
        "time": "02:30",
        "event": "NBA: Sacramento Kings @ Los Angeles Lakers",
        "streams": [
          "https://sportsonline.click/channels/hd/hd2.php"
        ]
      }
    ],
    "MONDAY": [
      {
        "time": "08:00",
        "event": "Melbourne Victory x Wellington Phoenix",
        "streams": [
          "https://sportsonline.click/channels/hd/hd2.php"
        ]
      },
      {
        "time": "16:00",
        "event": "Angola x Egypt",
        "streams": [
          "https://sportsonline.click/channels/hd/hd10.php",
          "https://sportsonline.click/channels/pt/sporttv1.php",
          "https://sportsonline.click/channels/bra/br3.php"
        ]
      },
      {
        "time": "16:00",
        "event": "Zimbabwe x South Africa",
        "streams": [
          "https://sportsonline.click/channels/hd/hd11.php",
          "https://sportsonline.click/channels/pt/sporttv2.php"
        ]
      },
      {
        "time": "18:00",
        "event": "Coventry City x Ipswich Town",
        "streams": [
          "https://sportsonline.click/channels/hd/hd1.php",
          "https://sportsonline.click/channels/pt/sporttv3.php"
        ]
      },
      {
        "time": "19:00",
        "event": "Comoros x Mali",
        "streams": [
          "https://sportsonline.click/channels/hd/hd10.php"
        ]
      },
      {
        "time": "19:00",
        "event": "Zambia x Morocco",
        "streams": [
          "https://sportsonline.click/channels/hd/hd11.php",
          "https://sportsonline.click/channels/bra/br3.php"
        ]
      },
      {
        "time": "19:45",
        "event": "Roma x Genoa",
        "streams": [
          "https://sportsonline.click/channels/hd/hd5.php",
          "https://sportsonline.click/channels/hd/hd7.php",
          "https://sportsonline.click/channels/pt/sporttv2.php",
          "https://sportsonline.click/channels/bra/br2.php"
        ]
      },
      {
        "time": "19:45",
        "event": "Wrexham x Preston North End",
        "streams": [
          "https://sportsonline.click/channels/hd/hd9.php",
          "https://sportsonline.click/channels/pt/sporttv4.php"
        ]
      },
      {
        "time": "20:15",
        "event": "Porto x AVS",
        "streams": [
          "https://sportsonline.click/channels/pt/sporttv1.php"
        ]
      },
      {
        "time": "20:15",
        "event": "Birmingham City x Southampton",
        "streams": [
          "https://sportsonline.click/channels/hd/hd1.php",
          "https://sportsonline.click/channels/pt/sporttv3.php"
        ]
      },
      {
        "time": "01:00",
        "event": "NBA: Cleveland Cavaliers @ San Antonio Spurs",
        "streams": [
          "https://sportsonline.click/channels/hd/hd2.php",
          "https://sportsonline.click/channels/pt/sporttv1.php",
          "https://sportsonline.click/channels/bra/br6.php"
        ]
      },
      {
        "time": "01:00",
        "event": "NFL: Los Angeles Rams @ Atlanta Falcons",
        "streams": [
          "https://sportsonline.click/channels/hd/hd1.php",
          "https://sportsonline.click/channels/bra/br4.php"
        ]
      },
      {
        "time": "03:30",
        "event": "NBA: Portland Trail Blazers @ Dallas Mavericks",
        "streams": [
          "https://sportsonline.click/channels/bra/br6.php"
        ]
      }
    ],
    "TUESDAY": [
      {
        "time": "15:15",
        "event": "Al Ahli x Al Fayha",
        "streams": [
          "https://sportsonline.click/channels/bra/br1.php"
        ]
      },
      {
        "time": "16:00",
        "event": "Uganda x Nigeria",
        "streams": [
          "https://sportsonline.click/channels/hd/hd11.php",
          "https://sportsonline.click/channels/pt/sporttv2.php",
          "https://sportsonline.click/channels/bra/br3.php"
        ]
      },
      {
        "time": "16:00",
        "event": "Tanzania x Tunisia",
        "streams": [
          "https://sportsonline.click/channels/hd/hd10.php",
          "https://sportsonline.click/channels/pt/sporttv3.php"
        ]
      },
      {
        "time": "17:30",
        "event": "Al Ittifaq x Al Nassr",
        "streams": [
          "https://sportsonline.click/channels/hd/hd9.php",
          "https://sportsonline.click/channels/pt/sporttv1.php",
          "https://sportsonline.click/channels/bra/br1.php"
        ]
      },
      {
        "time": "19:00",
        "event": "Botswana x Congo DR",
        "streams": [
          "https://sportsonline.click/channels/hd/hd10.php",
          "https://sportsonline.click/channels/pt/sporttv3.php"
        ]
      },
      {
        "time": "19:00",
        "event": "Benin x Senegal",
        "streams": [
          "https://sportsonline.click/channels/hd/hd11.php",
          "https://sportsonline.click/channels/pt/sporttv2.php",
          "https://sportsonline.click/channels/bra/br3.php"
        ]
      },
      {
        "time": "19:30",
        "event": "Chelsea x AFC Bournemouth",
        "streams": [
          "https://sportsonline.click/channels/hd/hd1.php",
          "https://sportsonline.click/channels/pt/eleven3.php",
          "https://sportsonline.click/channels/bra/br2.php"
        ]
      },
      {
        "time": "19:30",
        "event": "West Ham United x Brighton & Hove Albion",
        "streams": [
          "https://sportsonline.click/channels/hd/hd9.php"
        ]
      },
      {
        "time": "19:30",
        "event": "Nottingham Forest x Everton",
        "streams": [
          "https://sportsonline.click/channels/hd/hd8.php"
        ]
      },
      {
        "time": "19:30",
        "event": "Burnley x Newcastle United",
        "streams": [
          "https://sportsonline.click/channels/hd/hd4.php",
          "https://sportsonline.click/channels/bra/br4.php"
        ]
      },
      {
        "time": "20:00",
        "event": "Motherwell x Celtic",
        "streams": [
          "https://sportsonline.click/channels/hd/hd3.php",
          "https://sportsonline.click/channels/pt/sporttv4.php"
        ]
      },
      {
        "time": "20:15",
        "event": "Arsenal x Aston Villa",
        "streams": [
          "https://sportsonline.click/channels/hd/hd2.php",
          "https://sportsonline.click/channels/pt/eleven2.php",
          "https://sportsonline.click/channels/bra/br6.php"
        ]
      },
      {
        "time": "20:15",
        "event": "Manchester United x Wolverhampton Wanderers",
        "streams": [
          "https://sportsonline.click/channels/hd/hd5.php",
          "https://sportsonline.click/channels/pt/eleven1.php",
          "https://sportsonline.click/channels/bra/br5.php"
        ]
      },
      {
        "time": "20:15",
        "event": "Torreense x Lusitania FC Lourosa",
        "streams": [
          "https://sportsonline.click/channels/pt/sporttv1.php"
        ]
      },
      {
        "time": "01:00",
        "event": "NBA: Philadelphia 76ers @ Memphis Grizzlies",
        "streams": [
          "https://sportsonline.click/channels/hd/hd2.php"
        ]
      },
      {
        "time": "03:30",
        "event": "NBA: Detroit Pistons @ Los Angeles Lakers",
        "streams": [
          "https://sportsonline.click/channels/hd/hd2.php"
        ]
      }
    ]
  }
}