{
  "last_updated": "2026-04-18T01:24:02.754510Z",
  "events": {
    "FRIDAY": [
      {
        "time": "10:00",
        "event": "Tennis - ATP World Tour 500: Barcelona",
        "streams": [
          "https://v3.sportssonline.click/channels/pt/sporttv3.php"
        ]
      },
      {
        "time": "10:35",
        "event": "Melbourne Victory x Newcastle Jets",
        "streams": [
          "https://v3.sportssonline.click/channels/hd/hd10.php"
        ]
      },
      {
        "time": "12:00",
        "event": "Tennis - ATP World Tour 500: Barcelona",
        "streams": [
          "https://v3.sportssonline.click/channels/pt/sporttv3.php"
        ]
      },
      {
        "time": "13:00",
        "event": "Benfica U19 x Club Brugge U19",
        "streams": [
          "https://v3.sportssonline.click/channels/hd/hd5.php",
          "https://v3.sportssonline.click/channels/hd/hd6.php",
          "https://v3.sportssonline.click/channels/pt/eleven1.php"
        ]
      },
      {
        "time": "15:00",
        "event": "Tennis - ATP World Tour 500: Barcelona",
        "streams": [
          "https://v3.sportssonline.click/channels/pt/sporttv3.php"
        ]
      },
      {
        "time": "15:45",
        "event": "Al-Ahli x Johor Darul Ta'zim",
        "streams": [
          "https://v3.sportssonline.click/channels/hd/hd9.php"
        ]
      },
      {
        "time": "17:00",
        "event": "Zamalek x CR Belouizdad",
        "streams": [
          "https://v3.sportssonline.click/channels/hd/hd2.php"
        ]
      },
      {
        "time": "17:00",
        "event": "Tennis - ATP World Tour 500: Barcelona",
        "streams": [
          "https://v3.sportssonline.click/channels/pt/sporttv3.php"
        ]
      },
      {
        "time": "17:30",
        "event": "Sassuolo x Como",
        "streams": [
          "https://v3.sportssonline.click/channels/hd/hd7.php",
          "https://v3.sportssonline.click/channels/pt/sporttv2.php"
        ]
      },
      {
        "time": "17:30",
        "event": "Elversberg x Karlsruher",
        "streams": [
          "https://v3.sportssonline.click/channels/pt/eleven3.php"
        ]
      },
      {
        "time": "17:45",
        "event": "Real Madrid U19 x PSG U19",
        "streams": [
          "https://v3.sportssonline.click/channels/hd/hd5.php",
          "https://v3.sportssonline.click/channels/hd/hd6.php",
          "https://v3.sportssonline.click/channels/pt/eleven1.php"
        ]
      },
      {
        "time": "18:00",
        "event": "Fenerbahçe x Rizespor",
        "streams": [
          "https://v3.sportssonline.click/channels/hd/hd11.php",
          "https://v3.sportssonline.click/channels/pt/sporttv1.php"
        ]
      },
      {
        "time": "18:45",
        "event": "Academico Viseu x Feirense",
        "streams": [
          "https://v3.sportssonline.click/channels/pt/sporttv4.php"
        ]
      },
      {
        "time": "19:00",
        "event": "Machida Zelvia x Al Ittihad",
        "streams": [
          "https://v3.sportssonline.click/channels/hd/hd10.php",
          "https://v3.sportssonline.click/channels/bra/br6.php"
        ]
      },
      {
        "time": "19:30",
        "event": "St. Pauli x Köln",
        "streams": [
          "https://v3.sportssonline.click/channels/hd/hd3.php",
          "https://v3.sportssonline.click/channels/pt/eleven2.php"
        ]
      },
      {
        "time": "19:45",
        "event": "Internazionale x Cagliari",
        "streams": [
          "https://v3.sportssonline.click/channels/hd/hd8.php",
          "https://v3.sportssonline.click/channels/pt/sporttv2.php",
          "https://v3.sportssonline.click/channels/bra/br3.php"
        ]
      },
      {
        "time": "19:45",
        "event": "Lens x Toulouse",
        "streams": [
          "https://v3.sportssonline.click/channels/hd/hd2.php",
          "https://v3.sportssonline.click/channels/hd/hd4.php",
          "https://v3.sportssonline.click/channels/pt/sporttv3.php"
        ]
      },
      {
        "time": "20:00",
        "event": "Blackburn Rovers x Coventry City",
        "streams": [
          "https://v3.sportssonline.click/channels/bra/br2.php"
        ]
      },
      {
        "time": "20:45",
        "event": "Rio Ave x AVS",
        "streams": [
          "https://v3.sportssonline.click/channels/pt/sporttv1.php"
        ]
      },
      {
        "time": "00:30",
        "event": "Unión Santa Fe x Newell's Old Boys",
        "streams": [
          "https://v3.sportssonline.click/channels/hd/hd11.php"
        ]
      },
      {
        "time": "02:00",
        "event": "Mazatlán x Querétaro",
        "streams": [
          "https://v3.sportssonline.click/channels/hd/hd9.php"
        ]
      },
      {
        "time": "02:00",
        "event": "Power Slap 19: Las Vegas",
        "streams": [
          "https://v3.sportssonline.click/channels/pt/sporttv2.php"
        ]
      },
      {
        "time": "03:30",
        "event": "Vancouver Whitecaps x Sporting KC",
        "streams": [
          "https://v3.sportssonline.click/channels/hd/hd5.php"
        ]
      }
    ],
    "SATURDAY": [
      {
        "time": "11:00",
        "event": "Paços de Ferreira x Chaves",
        "streams": [
          "https://v3.sportssonline.click/channels/pt/sporttv1.php"
        ]
      },
      {
        "time": "12:00",
        "event": "Magdeburg x Fortuna Düsseldorf",
        "streams": [
          "https://v3.sportssonline.click/channels/hd/hd3.php"
        ]
      },
      {
        "time": "12:00",
        "event": "Dynamo Dresden x Bochum",
        "streams": [
          "https://v3.sportssonline.click/channels/hd/hd9.php"
        ]
      },
      {
        "time": "12:30",
        "event": "Brentford x Fulham",
        "streams": [
          "https://v3.sportssonline.click/channels/hd/hd1.php",
          "https://v3.sportssonline.click/channels/pt/eleven1.php"
        ]
      },
      {
        "time": "12:30",
        "event": "Dunfermline Athletic x Falkirk",
        "streams": [
          "https://v3.sportssonline.click/channels/hd/hd2.php"
        ]
      },
      {
        "time": "14:00",
        "event": "Udinese x Parma",
        "streams": [
          "https://v3.sportssonline.click/channels/hd/hd7.php",
          "https://v3.sportssonline.click/channels/pt/sporttv2.php"
        ]
      },
      {
        "time": "14:00",
        "event": "Mamelodi Sundowns x ES Tunis",
        "streams": [
          "https://v3.sportssonline.click/channels/hd/hd5.php"
        ]
      },
      {
        "time": "14:30",
        "event": "Hoffenheim x Borussia Dortmund",
        "streams": [
          "https://v3.sportssonline.click/channels/hd/hd3.php",
          "https://v3.sportssonline.click/channels/hd/hd6.php",
          "https://v3.sportssonline.click/channels/pt/eleven3.php"
        ]
      },
      {
        "time": "14:30",
        "event": "Union Berlin x Wolfsburg",
        "streams": [
          "https://v3.sportssonline.click/channels/hd/hd10.php"
        ]
      },
      {
        "time": "14:30",
        "event": "Bayer Leverkusen x Augsburg",
        "streams": [
          "https://v3.sportssonline.click/channels/hd/hd9.php"
        ]
      },
      {
        "time": "14:30",
        "event": "Werder Bremen x Hamburger SV",
        "streams": [
          "https://v3.sportssonline.click/channels/hd/hd4.php"
        ]
      },
      {
        "time": "15:00",
        "event": "Leeds United x Wolverhampton Wanderers",
        "streams": [
          "https://v3.sportssonline.click/channels/hd/hd11.php",
          "https://v3.sportssonline.click/channels/pt/eleven2.php"
        ]
      },
      {
        "time": "15:00",
        "event": "Newcastle United x AFC Bournemouth",
        "streams": [
          "https://v3.sportssonline.click/channels/hd/hd1.php",
          "https://v3.sportssonline.click/channels/pt/eleven1.php",
          "https://v3.sportssonline.click/channels/bra/br2.php"
        ]
      },
      {
        "time": "15:00",
        "event": "Spain W x Ukraine W",
        "streams": [
          "https://v3.sportssonline.click/channels/bra/br6.php"
        ]
      },
      {
        "time": "15:30",
        "event": "Nacional x Alverca",
        "streams": [
          "https://v3.sportssonline.click/channels/pt/sporttv1.php"
        ]
      },
      {
        "time": "16:00",
        "event": "Lorient x Olympique Marseille",
        "streams": [
          "https://v3.sportssonline.click/channels/hd/hd5.php",
          "https://v3.sportssonline.click/channels/pt/sporttv3.php"
        ]
      },
      {
        "time": "17:00",
        "event": "Napoli x Lazio",
        "streams": [
          "https://v3.sportssonline.click/channels/hd/hd7.php",
          "https://v3.sportssonline.click/channels/pt/sporttv2.php"
        ]
      },
      {
        "time": "17:15",
        "event": "Buriram United x Shabab Al Ahli",
        "streams": [
          "https://v3.sportssonline.click/channels/hd/hd11.php"
        ]
      },
      {
        "time": "17:30",
        "event": "Tottenham Hotspur x Brighton & Hove Albion",
        "streams": [
          "https://v3.sportssonline.click/channels/hd/hd1.php",
          "https://v3.sportssonline.click/channels/pt/eleven1.php",
          "https://v3.sportssonline.click/channels/bra/br2.php"
        ]
      },
      {
        "time": "17:30",
        "event": "Eintracht Frankfurt x RB Leipzig",
        "streams": [
          "https://v3.sportssonline.click/channels/hd/hd3.php",
          "https://v3.sportssonline.click/channels/pt/eleven2.php",
          "https://v3.sportssonline.click/channels/bra/br1.php"
        ]
      },
      {
        "time": "18:00",
        "event": "Gençlerbirliği x Galatasaray",
        "streams": [
          "https://v3.sportssonline.click/channels/hd/hd5.php",
          "https://v3.sportssonline.click/channels/bra/br6.php"
        ]
      },
      {
        "time": "18:00",
        "event": "Angers SCO x Le Havre",
        "streams": [
          "https://v3.sportssonline.click/channels/hd/hd4.php",
          "https://v3.sportssonline.click/channels/pt/sporttv3.php"
        ]
      },
      {
        "time": "18:00",
        "event": "Casa Pia x Santa Clara",
        "streams": [
          "https://v3.sportssonline.click/channels/pt/sporttv1.php"
        ]
      },
      {
        "time": "18:00",
        "event": "Panaitolikos x Panserraikos",
        "streams": [
          "https://v3.sportssonline.click/channels/hd/hd9.php"
        ]
      },
      {
        "time": "19:00",
        "event": "Gimnasia La Plata x Estudiantes Río Cuarto",
        "streams": [
          "https://v3.sportssonline.click/channels/hd/hd11.php"
        ]
      },
      {
        "time": "19:30",
        "event": "St. Pauli x Köln",
        "streams": [
          "https://v3.sportssonline.click/channels/pt/eleven2.php"
        ]
      },
      {
        "time": "19:30",
        "event": "Hannover 96 x Paderborn",
        "streams": [
          "https://v3.sportssonline.click/channels/hd/hd10.php"
        ]
      },
      {
        "time": "19:45",
        "event": "Roma x Atalanta",
        "streams": [
          "https://v3.sportssonline.click/channels/hd/hd7.php",
          "https://v3.sportssonline.click/channels/bra/br2.php"
        ]
      },
      {
        "time": "20:00",
        "event": "Chelsea x Manchester United",
        "streams": [
          "https://v3.sportssonline.click/channels/hd/hd1.php",
          "https://v3.sportssonline.click/channels/pt/eleven1.php",
          "https://v3.sportssonline.click/channels/bra/br3.php"
        ]
      },
      {
        "time": "20:00",
        "event": "RSB Berkane x FAR Rabat",
        "streams": [
          "https://v3.sportssonline.click/channels/hd/hd5.php"
        ]
      },
      {
        "time": "20:00",
        "event": "Atlético Madrid x Real Sociedad",
        "streams": [
          "https://v3.sportssonline.click/channels/hd/hd2.php",
          "https://v3.sportssonline.click/channels/hd/hd6.php",
          "https://v3.sportssonline.click/channels/pt/sporttv2.php",
          "https://v3.sportssonline.click/channels/bra/br6.php"
        ]
      },
      {
        "time": "20:05",
        "event": "Lille x Nice",
        "streams": [
          "https://v3.sportssonline.click/channels/hd/hd4.php",
          "https://v3.sportssonline.click/channels/pt/sporttv3.php"
        ]
      },
      {
        "time": "20:30",
        "event": "Gil Vicente x Vitória Guimarães",
        "streams": [
          "https://v3.sportssonline.click/channels/pt/sporttv1.php"
        ]
      },
      {
        "time": "21:00",
        "event": "Basketball: Esgueira x Benfica",
        "streams": [
          "https://v3.sportssonline.click/channels/pt/eleven1.php"
        ]
      },
      {
        "time": "21:15",
        "event": "Instituto x Estudiantes",
        "streams": [
          "https://v3.sportssonline.click/channels/hd/hd8.php"
        ]
      },
      {
        "time": "21:30",
        "event": "Colorado Rapids x Inter Miami",
        "streams": [
          "https://v3.sportssonline.click/channels/hd/hd9.php"
        ]
      },
      {
        "time": "22:00",
        "event": "América-MG x Sport",
        "streams": [
          "https://v3.sportssonline.click/channels/bra/br2.php"
        ]
      },
      {
        "time": "22:30",
        "event": "Everton x Universidad Chile",
        "streams": [
          "https://v3.sportssonline.click/channels/hd/hd10.php"
        ]
      },
      {
        "time": "22:30",
        "event": "Vasco da Gama x São Paulo",
        "streams": [
          "https://v3.sportssonline.click/channels/bra/br4.php"
        ]
      },
      {
        "time": "22:30",
        "event": "Chapecoense x Botafogo",
        "streams": [
          "https://v3.sportssonline.click/channels/bra/br5.php"
        ]
      },
      {
        "time": "23:00",
        "event": "UFC Fight Night: Prelims",
        "streams": [
          "https://v3.sportssonline.click/channels/hd/hd1.php"
        ]
      },
      {
        "time": "23:30",
        "event": "Independiente x Defensa y Justicia",
        "streams": [
          "https://v3.sportssonline.click/channels/hd/hd11.php",
          "https://v3.sportssonline.click/channels/bra/br6.php"
        ]
      },
      {
        "time": "00:00",
        "event": "Cruz Azul x Tijuana",
        "streams": [
          "https://v3.sportssonline.click/channels/hd/hd9.php"
        ]
      },
      {
        "time": "00:00",
        "event": "Vitória x Corinthians",
        "streams": [
          "https://v3.sportssonline.click/channels/bra/br1.php"
        ]
      },
      {
        "time": "00:30",
        "event": "Cruzeiro x Grêmio",
        "streams": [
          "https://v3.sportssonline.click/channels/bra/br3.php"
        ]
      },
      {
        "time": "01:00",
        "event": "Deportes Concepción x La Serena",
        "streams": [
          "https://v3.sportssonline.click/channels/hd/hd10.php"
        ]
      },
      {
        "time": "01:00",
        "event": "UFC Fight Night: Gilbert Burns vs Mike Malot",
        "streams": [
          "https://v3.sportssonline.click/channels/hd/hd1.php",
          "https://v3.sportssonline.click/channels/pt/sporttv1.php"
        ]
      },
      {
        "time": "01:30",
        "event": "NBA: Houston Rockets @ Los Angeles Lakers",
        "streams": [
          "https://v3.sportssonline.click/channels/pt/sporttv2.php"
        ]
      },
      {
        "time": "01:45",
        "event": "Argentinos Juniors x Atlético Tucumán",
        "streams": [
          "https://v3.sportssonline.click/channels/hd/hd8.php"
        ]
      },
      {
        "time": "02:00",
        "event": "Brazil W x Canada W",
        "streams": [
          "https://v3.sportssonline.click/channels/bra/br1.php"
        ]
      },
      {
        "time": "02:05",
        "event": "Monterrey x Pachuca",
        "streams": [
          "https://v3.sportssonline.click/channels/hd/hd9.php"
        ]
      },
      {
        "time": "04:10",
        "event": "América x Toluca",
        "streams": [
          "https://v3.sportssonline.click/channels/hd/hd9.php"
        ]
      }
    ]
  }
}