[
  {
    "source_url": "https://streamtpmedia.com/global1.php?stream=tudn_usa",
    "extracted_at": "2025-11-23T19:19:48.007491",
    "status": "error",
    "error": "Extraction failed: No iframe found on the page"
  },
  {
    "source_url": "https://sportzonline.live/channels/hd/hd9.php",
    "extracted_at": "2025-11-23T19:19:48.007491",
    "status": "success",
    "data": {
      "destination_url": "https://qbkunwt.234276133.fit:8443/hls/mhbq0m7am17nhai.m3u8?s=NqnGT7Ha-i5S4e15TVW3QQ&e=1763947189",
      "request_headers": {
        "Referer": "https://outfitreferee.net/embed/mhbq0m7am17nhai",
        "User-Agent": "Mozilla/5.0 (Windows NT 10.0; Win64; x64) AppleWebKit/537.36 (KHTML, like Gecko) Chrome/124.0 Safari/537.36"
      },
      "mediaflow_endpoint": "hls_manifest_proxy"
    }
  }
]